metanetx_sdk/__init__.py
metanetx_sdk/_version.py
metanetx_sdk/api.py
metanetx_sdk/extract.py
metanetx_sdk/ftp.py
metanetx_sdk/helpers.py
metanetx_sdk/report.py
metanetx_sdk/cli/__init__.py
metanetx_sdk/cli/cli.py
metanetx_sdk/cli/etl.py
metanetx_sdk/data/__init__.py
metanetx_sdk/data/chem_prefix.tsv
metanetx_sdk/data/comp_prefix.tsv
metanetx_sdk/data/metanetx.toml
metanetx_sdk/data/reac_prefix.tsv
metanetx_sdk/model/__init__.py
metanetx_sdk/model/ftp_configuration_model.py
metanetx_sdk/model/path_info_model.py
metanetx_sdk/model/table_configuration_model.py
metanetx_sdk/transform/__init__.py
metanetx_sdk/transform/chemical.py
metanetx_sdk/transform/compartment.py
metanetx_sdk/transform/helpers.py
metanetx_sdk/transform/reaction.py
metanetx_sdk-4.2.0.dist-info/LICENSE
metanetx_sdk-4.2.0.dist-info/METADATA
metanetx_sdk-4.2.0.dist-info/WHEEL
metanetx_sdk-4.2.0.dist-info/entry_points.txt
metanetx_sdk-4.2.0.dist-info/top_level.txt
metanetx_sdk-4.2.0.dist-info/zip-safe
metanetx_sdk-4.2.0.dist-info/RECORD
