Metadata-Version: 2.1
Name: metanetx-sdk
Version: 4.2.0
Summary: Parse and clean up information from MetaNetX (https://metanetx.org).
Home-page: https://github.com/Midnighter/metanetx-sdk
Author: Moritz E. Beber
Author-email: midnighter@posteo.net
License: Apache-2.0
Download-URL: https://pypi.org/project/metanetx-sdk/
Project-URL: Source Code, https://github.com/Midnighter/metanetx-sdk
Project-URL: Bug Tracker, https://github.com/Midnighter/metanetx-sdk/issues
Keywords: MetaNetX,SDK,MIRIAM,Identifiers.org
Platform: UNKNOWN
Classifier: Development Status :: 4 - Beta
Classifier: Environment :: Console
Classifier: Intended Audience :: Science/Research
Classifier: License :: OSI Approved :: Apache Software License
Classifier: Natural Language :: English
Classifier: Operating System :: OS Independent
Classifier: Programming Language :: Python :: 3 :: Only
Classifier: Programming Language :: Python :: 3.8
Classifier: Programming Language :: Python :: 3.9
Classifier: Topic :: Scientific/Engineering :: Bio-Informatics
Classifier: Typing :: Typed
Requires-Python: >=3.8
License-File: LICENSE
Requires-Dist: aioftp (~=0.18)
Requires-Dist: click (~=7.0)
Requires-Dist: click-log (~=0.3)
Requires-Dist: depinfo (~=1.5)
Requires-Dist: pandas (~=1.0)
Requires-Dist: pydantic (~=1.6)
Requires-Dist: python-dateutil (~=2.8)
Requires-Dist: pytz
Requires-Dist: toml (~=0.10)
Provides-Extra: development
Requires-Dist: black ; extra == 'development'
Requires-Dist: isort ; extra == 'development'
Requires-Dist: pep517 ; extra == 'development'
Requires-Dist: tox ; extra == 'development'
Requires-Dist: twine ; extra == 'development'
Provides-Extra: reporting
Requires-Dist: humanize ; extra == 'reporting'
Requires-Dist: ipywidgets ; extra == 'reporting'
Requires-Dist: jupyterlab ; extra == 'reporting'
Requires-Dist: plotly ; extra == 'reporting'
